clarite/__init__.py
clarite/cli/__init__.py
clarite/cli/cli.py
clarite/cli/commands/__init__.py
clarite/cli/commands/analyze.py
clarite/cli/commands/describe.py
clarite/cli/commands/load.py
clarite/cli/commands/modify.py
clarite/cli/commands/plot.py
clarite/cli/custom_types.py
clarite/cli/parameters.py
clarite/internal/__init__.py
clarite/internal/calculations.py
clarite/internal/utilities.py
clarite/modules/__init__.py
clarite/modules/analyze/__init__.py
clarite/modules/analyze/association_study.py
clarite/modules/analyze/ewas.py
clarite/modules/analyze/interaction_study.py
clarite/modules/analyze/regression/__init__.py
clarite/modules/analyze/regression/base.py
clarite/modules/analyze/regression/glm_regression.py
clarite/modules/analyze/regression/interaction_regression.py
clarite/modules/analyze/regression/r_code/__init__.py
clarite/modules/analyze/regression/r_code/ewas_r.R
clarite/modules/analyze/regression/r_code/r_utilities.py
clarite/modules/analyze/regression/r_survey_regression.py
clarite/modules/analyze/regression/weighted_glm_regression.py
clarite/modules/analyze/utils.py
clarite/modules/describe.py
clarite/modules/load.py
clarite/modules/modify.py
clarite/modules/plot/__init__.py
clarite/modules/plot/distributions.py
clarite/modules/plot/histogram.py
clarite/modules/plot/manhattan.py
clarite/modules/plot/top_results.py
clarite/modules/survey/LICENSE
clarite/modules/survey/__init__.py
clarite/modules/survey/survey_design.py
clarite/modules/survey/survey_model.py
clarite-2.4.1.dist-info/AUTHORS.rst
clarite-2.4.1.dist-info/LICENSE
clarite-2.4.1.dist-info/METADATA
clarite-2.4.1.dist-info/WHEEL
clarite-2.4.1.dist-info/entry_points.txt
clarite-2.4.1.dist-info/RECORD
