Metadata-Version: 2.1
Name: clarite
Version: 2.4.1
Summary: CLeaning to Analysis: Reproducibility-based Interface for Traits and Exposures
Home-page: https://github.com/HallLab/clarite-python/
License: BSD-3-Clause
Author: Andre Rico
Author-email: andreluis.rico@pennmedicine.upenn.edu
Requires-Python: >=3.10,<3.13
Classifier: Development Status :: 4 - Beta
Classifier: Intended Audience :: Science/Research
Classifier: License :: OSI Approved :: BSD License
Classifier: Programming Language :: Python :: 3
Classifier: Programming Language :: Python :: 3.10
Classifier: Programming Language :: Python :: 3.11
Classifier: Programming Language :: Python :: 3.12
Classifier: Topic :: Scientific/Engineering :: Bio-Informatics
Provides-Extra: docs
Requires-Dist: click (>7)
Requires-Dist: ipython (>=8.24,<9.0) ; extra == "docs"
Requires-Dist: matplotlib (>=3.4.2,<4.0.0)
Requires-Dist: numpy (>=1.24,<2.0)
Requires-Dist: numpydoc (>=1.1.0,<2.0.0) ; extra == "docs"
Requires-Dist: pandas (>=2.2,<3.0)
Requires-Dist: pandas-genomics (>=1.0.0,<2.0.0)
Requires-Dist: rpy2 (>=3.6.0,<4.0.0)
Requires-Dist: scipy (>=1.9,<2.0)
Requires-Dist: seaborn (>0.9)
Requires-Dist: statsmodels (>=0.14,<0.15)
Requires-Dist: tzlocal (>=2.1,<3.0)
Project-URL: Documentation, https://clarite-python.readthedocs.io/en/latest/
Project-URL: Repository, https://github.com/HallLab/clarite-python/
